sql1/__init__.py
sql1/core/__init__.py
sql1/core/core.py
sql1/sql_class/__init__.py
sql1/sql_class/sql_class.py
sql1/types/__init__.py
sql1/types/types.py
sql1-0.1.3.dist-info/LICENSE
sql1-0.1.3.dist-info/METADATA
sql1-0.1.3.dist-info/WHEEL
sql1-0.1.3.dist-info/top_level.txt
sql1-0.1.3.dist-info/RECORD
