Metadata-Version: 2.2
Name: sql1
Version: 0.1.3
Summary: An asynchronous Python ORM that supports MySQL, SQLite, and PostgreSQL with robust performance and easy-to-use interface.
Home-page: https://github.com/NuoQte/sql1
Author: NuoQTe
Author-email: nuoqte@gmail.com
License: MIT
License-File: LICENSE
Requires-Dist: APScheduler==3.10.4
Dynamic: author
Dynamic: author-email
Dynamic: description
Dynamic: description-content-type
Dynamic: home-page
Dynamic: license
Dynamic: requires-dist
Dynamic: summary
